makefilename/__init__.py
makefilename/main.py
makefilename-0.1.1.dist-info/METADATA
makefilename-0.1.1.dist-info/WHEEL
makefilename-0.1.1.dist-info/RECORD
